edx_repo_tools/__init__.py
edx_repo_tools/add_common_constraint.py
edx_repo_tools/auth.py
edx_repo_tools/data.py
edx_repo_tools/dependabot_yml.py
edx_repo_tools/helpers.py
edx_repo_tools/modernize_openedx_yaml.py
edx_repo_tools/utils.py
edx_repo_tools/audit_gh_users/__init__.py
edx_repo_tools/audit_gh_users/audit_users.py
edx_repo_tools/codemods/__init__.py
edx_repo_tools/codemods/django2/__init__.py
edx_repo_tools/codemods/django2/auth_anonymous_update.py
edx_repo_tools/codemods/django2/foreignkey_on_delete_mod.py
edx_repo_tools/codemods/django2/widget_add_renderer_mod.py
edx_repo_tools/codemods/django3/__init__.py
edx_repo_tools/codemods/django3/add_new_django32_settings.py
edx_repo_tools/codemods/django3/github_actions_modernizer.py
edx_repo_tools/codemods/django3/github_actions_modernizer_django.py
edx_repo_tools/codemods/django3/remove_python2_unicode_compatible.py
edx_repo_tools/codemods/django3/replace_render_to_response.py
edx_repo_tools/codemods/django3/replace_static.py
edx_repo_tools/codemods/django3/replace_unicode_with_str.py
edx_repo_tools/codemods/django3/setup_file_modernizer.py
edx_repo_tools/codemods/django3/tox_modernizer.py
edx_repo_tools/codemods/django3/travis_modernizer.py
edx_repo_tools/codemods/node16/__init__.py
edx_repo_tools/codemods/node16/gha_ci_modernizer.py
edx_repo_tools/codemods/node16/gha_release_workflow_modernizer.py
edx_repo_tools/codemods/python312/__init__.py
edx_repo_tools/codemods/python312/gh_actions_modernizer.py
edx_repo_tools/codemods/python312/tox_modernizer.py
edx_repo_tools/conventional_commits/__init__.py
edx_repo_tools/conventional_commits/commitstats.py
edx_repo_tools/dev/__init__.py
edx_repo_tools/dev/clone_org.py
edx_repo_tools/dev/get_org_repo_urls.py
edx_repo_tools/dev/show_hooks.py
edx_repo_tools/find_dependencies/__init__.py
edx_repo_tools/find_dependencies/find_dependencies.py
edx_repo_tools/find_dependencies/find_python_dependencies.py
edx_repo_tools/gitgraft/__init__.py
edx_repo_tools/gitgraft/gitgraft.py
edx_repo_tools-3.0.1.dist-info/LICENSE.txt
edx_repo_tools-3.0.1.dist-info/METADATA
edx_repo_tools-3.0.1.dist-info/NOTICE.txt
edx_repo_tools-3.0.1.dist-info/WHEEL
edx_repo_tools-3.0.1.dist-info/entry_points.txt
edx_repo_tools-3.0.1.dist-info/top_level.txt
edx_repo_tools-3.0.1.dist-info/RECORD
